aie/__init__.py
aie/auth.py
aie/env.py
aie/g_var.py
aie/client/__init__.py
aie/error/__init__.py
aie_sdk-3.0.4.dist-info/METADATA
aie_sdk-3.0.4.dist-info/WHEEL
aie_sdk-3.0.4.dist-info/top_level.txt
aie_sdk-3.0.4.dist-info/RECORD
