Metadata-Version: 2.1
Name: aie-sdk
Version: 3.0.4
Summary: AIEarth Engine Python SDK
Home-page: https://engine-aiearth.aliyun.com/
Requires-Python: >=3.8.0
Requires-Dist: aie-ipyleaflet
Requires-Dist: jinja2
Requires-Dist: black
Requires-Dist: oss2
Requires-Dist: matplotlib
Requires-Dist: bqplot
Requires-Dist: pyyaml
Requires-Dist: pystac-client
Requires-Dist: pandas
Requires-Dist: aiearth-core
Requires-Dist: aiearth-engine
Provides-Extra: data
Requires-Dist: aiearth-core (>=1.0.1) ; extra == 'data'
Requires-Dist: aiearth-data ; extra == 'data'
Provides-Extra: engine
Requires-Dist: aiearth-core ; extra == 'engine'
Requires-Dist: aie-ipyleaflet ; extra == 'engine'
Requires-Dist: aiearth-engine ; extra == 'engine'
Requires-Dist: notebook (<7) ; extra == 'engine'
Requires-Dist: aie-sdk (>=3.0.3) ; extra == 'engine'
Provides-Extra: openapi
Requires-Dist: aiearth-openapi (>=1.1.0) ; extra == 'openapi'
Requires-Dist: alibabacloud-aiearth-engine20220609 (>=1.0.6) ; extra == 'openapi'
